<?xml version="1.0" encoding="utf-8"?>
<ArrayOfOrder xmlns:xsi="http://www.w3.org/2001/XMLSchema-instance" xmlns:xsd="http://www.w3.org/2001/XMLSchema">
  <Order>
    <OrderId>0</OrderId>
    <RestaurantId>0</RestaurantId>
    <UserEmail>dominic.dolan@hotmail.com</UserEmail>
  </Order>
  <Order>
    <OrderId>1</OrderId>
    <RestaurantId>0</RestaurantId>
    <UserEmail>dominic.dolan@hotmail.com</UserEmail>
  </Order>
  <Order>
    <OrderId>2</OrderId>
    <RestaurantId>0</RestaurantId>
    <UserEmail>dominic.dolan@hotmail.com</UserEmail>
  </Order>
  <Order>
    <OrderId>3</OrderId>
    <RestaurantId>0</RestaurantId>
    <UserEmail>dominic.dolan@hotmail.com</UserEmail>
  </Order>
  <Order>
    <OrderId>4</OrderId>
    <RestaurantId>0</RestaurantId>
    <UserEmail>dominic.dolan@hotmail.com</UserEmail>
  </Order>
  <Order>
    <OrderId>5</OrderId>
    <RestaurantId>0</RestaurantId>
    <UserEmail>dominic.dolan@hotmail.com</UserEmail>
  </Order>
  <Order>
    <OrderId>6</OrderId>
    <RestaurantId>0</RestaurantId>
    <UserEmail>dominic.dolan@hotmail.com</UserEmail>
    <CustomerAddress>123 street, Some Lane, Dublin, Dublin, D01TA49</CustomerAddress>
  </Order>
  <Order>
    <OrderId>7</OrderId>
    <RestaurantId>0</RestaurantId>
    <UserEmail>dominic.dolan@hotmail.com</UserEmail>
    <CustomerAddress>123 street, Some Lane, Dublin, Dublin, D01TA49</CustomerAddress>
  </Order>
  <Order>
    <OrderId>8</OrderId>
    <RestaurantId>0</RestaurantId>
    <UserEmail>dominic.dolan@hotmail.com</UserEmail>
    <CustomerAddress>123 street, Some Lane, Dublin, Dublin, D01TA49</CustomerAddress>
  </Order>
  <Order>
    <OrderId>9</OrderId>
    <RestaurantId>1</RestaurantId>
    <UserEmail>dominic.dolan@hotmail.com</UserEmail>
    <CustomerAddress>123 street, Some Lane, Dublin, Dublin, D01TA49</CustomerAddress>
  </Order>
  <Order>
    <OrderId>10</OrderId>
    <RestaurantId>1</RestaurantId>
    <UserEmail>dominic.dolan@hotmail.com</UserEmail>
    <CustomerAddress>123 street, Some Lane, Dublin, Dublin, D01TA49</CustomerAddress>
  </Order>
  <Order>
    <OrderId>11</OrderId>
    <RestaurantId>1</RestaurantId>
    <UserEmail>dominic.dolan@hotmail.com</UserEmail>
    <CustomerAddress>123 street, Some Lane, Dublin, Dublin, D01TA49</CustomerAddress>
  </Order>
</ArrayOfOrder>